CHANGES.txt
LICENSE.txt
MANIFEST.in
README.md
requirements.txt
setup.py
iloveck101/__init__.py
iloveck101/__init__.pyc
iloveck101/iloveck101.py
iloveck101/iloveck101.pyc
iloveck101/utils.py
iloveck101/utils.pyc
iloveck101.egg-info/PKG-INFO
iloveck101.egg-info/SOURCES.txt
iloveck101.egg-info/dependency_links.txt
iloveck101.egg-info/entry_points.txt
iloveck101.egg-info/requires.txt
iloveck101.egg-info/top_level.txt