Metadata-Version: 1.0
Name: iloveck101
Version: 0.5.2
Summary: Download images from ck101 thread
Home-page: https://github.com/tzangms/iloveck101
Author: tzangms
Author-email: tzangms@gmail.com
License: LICENSE.txt
Platform: UNKNOWN
